gapstatistics/.ipynb_checkpoints/gapstatistics-checkpoint.py
gapstatistics/__init__.py
gapstatistics/gapstatistics.py
gapstatistics-0.1.5.dist-info/LICENSE
gapstatistics-0.1.5.dist-info/METADATA
gapstatistics-0.1.5.dist-info/WHEEL
gapstatistics-0.1.5.dist-info/RECORD
