Metadata-Version: 2.1
Name: gapstatistics
Version: 0.1.5
Summary: A library for calculating the gap statistics for clustering algorithms
Home-page: https://github.com/Mavengence/GapStatistics
License: MIT
Author: Tim Loehr
Author-email: timloehr@icloud.com
Classifier: License :: OSI Approved :: MIT License
Classifier: Programming Language :: Python :: 2
Classifier: Programming Language :: Python :: 2.7
Classifier: Programming Language :: Python :: 3
Classifier: Programming Language :: Python :: 3.4
Classifier: Programming Language :: Python :: 3.5
Classifier: Programming Language :: Python :: 3.6
Classifier: Programming Language :: Python :: 3.7
Classifier: Programming Language :: Python :: 3.8
Classifier: Programming Language :: Python :: 3.9
Classifier: Programming Language :: Python :: 3.10
Classifier: Programming Language :: Python :: 3.11
Classifier: Programming Language :: Python :: 3.12
Project-URL: Repository, https://github.com/Mavengence/GapStatistics
